LICENSE
setup.py
i3_auto_floating/__init__.py
i3_auto_floating/auto_floating.py
i3_auto_floating/shared.py
i3_auto_floating/toggle_floating.py
i3_auto_floating.egg-info/PKG-INFO
i3_auto_floating.egg-info/SOURCES.txt
i3_auto_floating.egg-info/dependency_links.txt
i3_auto_floating.egg-info/entry_points.txt
i3_auto_floating.egg-info/requires.txt
i3_auto_floating.egg-info/top_level.txt