Metadata-Version: 2.4
Name: i3_auto_floating
Version: 1.4
Summary: Remember floating state of i3wm and Sway windows and automatically set it when a new window of the same app is created.
Home-page: https://github.com/artemave/i3_auto_floating
Author: Artem Avetisyan
License: MIT
License-File: LICENSE
Requires-Dist: i3ipc>=2.2.1
Dynamic: author
Dynamic: home-page
Dynamic: license
Dynamic: license-file
Dynamic: requires-dist
Dynamic: summary
